pyutilscr/__init__.py
pyutilscr/check.py
pyutilscr/log.py
pyutilscr/pinfo.py
pyutilscr/source.py
pyutils_cr-0.1.3.dist-info/LICENSE
pyutils_cr-0.1.3.dist-info/METADATA
pyutils_cr-0.1.3.dist-info/WHEEL
pyutils_cr-0.1.3.dist-info/top_level.txt
pyutils_cr-0.1.3.dist-info/RECORD
