Metadata-Version: 2.1
Name: pyutils-cr
Version: 0.1.3
Summary: A simple package that contains extremely useful utilities.
Home-page: https://github.com/GoodMusic8596/pyutilscr
Author: Crow Randalf
Author-email: somethings8596@gmail.com
License: UNKNOWN
Platform: UNKNOWN
Classifier: Programming Language :: Python :: 3
Classifier: License :: OSI Approved :: MIT License
Classifier: Operating System :: OS Independent
Requires-Python: >=3.6
